{
  "providers": {
    "awscloudformation": {
      "AuthRoleName": "amplify-fotoapp-dev-161236-authRole",
      "UnauthRoleArn": "arn:aws:iam::492846829231:role/amplify-fotoapp-dev-161236-unauthRole",
      "AuthRoleArn": "arn:aws:iam::492846829231:role/amplify-fotoapp-dev-161236-authRole",
      "Region": "eu-central-1",
      "DeploymentBucketName": "amplify-fotoapp-dev-161236-deployment",
      "UnauthRoleName": "amplify-fotoapp-dev-161236-unauthRole",
      "StackName": "amplify-fotoapp-dev-161236",
      "StackId": "arn:aws:cloudformation:eu-central-1:492846829231:stack/amplify-fotoapp-dev-161236/0a5d2430-8b21-11eb-8f2f-027b939ca8b0",
      "AmplifyAppId": "d31iq95e8f17vj"
    }
  },
  "auth": {
    "fotoappdbb72470": {
      "service": "Cognito",
      "providerPlugin": "awscloudformation",
      "dependsOn": [],
      "customAuth": false,
      "providerMetadata": {
        "s3TemplateURL": "https://s3.amazonaws.com/amplify-fotoapp-dev-161236-deployment/amplify-cfn-templates/auth/fotoappdbb72470-cloudformation-template.yml",
        "logicalId": "authfotoappdbb72470"
      },
      "lastPushTimeStamp": "2021-03-22T15:51:46.830Z",
      "output": {
        "UserPoolId": "eu-central-1_l4pJ75B3q",
        "AppClientIDWeb": "7d0ufr1a3v5hdhkj8ah2veot9r",
        "AppClientID": "39baebd6u9mcs4qtlr1434vd9d",
        "IdentityPoolId": "eu-central-1:84d8ef2d-593a-4246-b963-9a45128980a7",
        "IdentityPoolName": "fotoappdbb72470_identitypool_dbb72470__dev",
        "UserPoolName": "fotoappdbb72470_userpool_dbb72470"
      },
      "lastPushDirHash": "MrXbFNnLK7ZK+ruC93xhf6Tzv5k="
    }
  }
}